pytextdataclean/__init__.py
pytextdataclean/textclean.py
py_text_data_clean-0.0.5.dist-info/LICENSE
py_text_data_clean-0.0.5.dist-info/METADATA
py_text_data_clean-0.0.5.dist-info/WHEEL
py_text_data_clean-0.0.5.dist-info/top_level.txt
py_text_data_clean-0.0.5.dist-info/RECORD
