Metadata-Version: 2.1
Name: py-text-data-clean
Version: 0.0.5
Summary: Text Data Cleaning
Home-page: https://github.com/Sandeep-Panchal/Python-Text-Data-Clean
Author: Sandeep Panchal
Author-email: sandeep.panchal545@gmail.com
License: UNKNOWN
Project-URL: Bug Tracker, https://github.com/Sandeep-Panchal/Python-Text-Data-Clean/issues
Keywords: "text data clean"
Platform: UNKNOWN
Classifier: Programming Language :: Python :: 3
Classifier: License :: OSI Approved :: MIT License
Classifier: Operating System :: OS Independent
Classifier: Intended Audience :: Developers
Requires-Python: >=3
License-File: LICENSE
